pytest_job_selection.py
pytest_job_selection-0.1.2.dist-info/LICENSE
pytest_job_selection-0.1.2.dist-info/METADATA
pytest_job_selection-0.1.2.dist-info/WHEEL
pytest_job_selection-0.1.2.dist-info/entry_points.txt
pytest_job_selection-0.1.2.dist-info/top_level.txt
pytest_job_selection-0.1.2.dist-info/RECORD
