Metadata-Version: 2.1
Name: pytest-job-selection
Version: 0.1.2
Summary: A pytest plugin for load balancing test suites
Home-page: https://gitlab.com/arvidnl/pytest-job-selection
Author: Arvid Jakobsson
Author-email: arvid.jakobsson@nomadic-labs.com
Maintainer: Arvid Jakobsson
Maintainer-email: arvid.jakobsson@nomadic-labs.com
License: MIT
Classifier: Development Status :: 4 - Beta
Classifier: Framework :: Pytest
Classifier: Intended Audience :: Developers
Classifier: Topic :: Software Development :: Testing
Classifier: Programming Language :: Python
Classifier: Programming Language :: Python :: 3
Classifier: Programming Language :: Python :: 3.5
Classifier: Programming Language :: Python :: 3.6
Classifier: Programming Language :: Python :: 3.7
Classifier: Programming Language :: Python :: 3.8
Classifier: Programming Language :: Python :: 3 :: Only
Classifier: Programming Language :: Python :: Implementation :: CPython
Classifier: Programming Language :: Python :: Implementation :: PyPy
Classifier: Operating System :: OS Independent
Classifier: License :: OSI Approved :: MIT License
Requires-Python: >=3.5
License-File: LICENSE
Requires-Dist: pytest (>=3.5.0)
Requires-Dist: typing-extensions (>=4.4.0)
Provides-Extra: dev
Requires-Dist: cram (>=0.6) ; extra == 'dev'
